chain_factory/__init__.py
chain_factory/task_queue/__init__.py
chain_factory/task_queue/blocked_handler.py
chain_factory/task_queue/cluster_heartbeat.py
chain_factory/task_queue/list_handler.py
chain_factory/task_queue/queue_handler.py
chain_factory/task_queue/task_handler.py
chain_factory/task_queue/task_queue.py
chain_factory/task_queue/task_runner.py
chain_factory/task_queue/wait_handler.py
chain_factory/task_queue/common/__init__.py
chain_factory/task_queue/common/generate_random_id.py
chain_factory/task_queue/common/settings.py
chain_factory/task_queue/common/task_return_type.py
chain_factory/task_queue/decorators/__init__.py
chain_factory/task_queue/decorators/parse_catcher.py
chain_factory/task_queue/decorators/repeat.py
chain_factory/task_queue/models/__init__.py
chain_factory/task_queue/models/etc/__init__.py
chain_factory/task_queue/models/etc/list_item_container.py
chain_factory/task_queue/models/mongo/__init__.py
chain_factory/task_queue/models/mongo/node.py
chain_factory/task_queue/models/mongo/node_tasks.py
chain_factory/task_queue/models/mongo/registered_task.py
chain_factory/task_queue/models/mongo/task.py
chain_factory/task_queue/models/mongo/task_log.py
chain_factory/task_queue/models/mongo/task_workflow_association.py
chain_factory/task_queue/models/mongo/workflow.py
chain_factory/task_queue/models/mongo/workflow_log.py
chain_factory/task_queue/models/redis/__init__.py
chain_factory/task_queue/models/redis/heartbeat.py
chain_factory/task_queue/models/redis/task_control_message.py
chain_factory/task_queue/models/redis/task_log_status.py
chain_factory/task_queue/models/redis/task_status.py
chain_factory/task_queue/models/redis/workflow_status.py
chain_factory/task_queue/wrapper/__init__.py
chain_factory/task_queue/wrapper/amqp.py
chain_factory/task_queue/wrapper/bytes_io_wrapper.py
chain_factory/task_queue/wrapper/interruptable_thread.py
chain_factory/task_queue/wrapper/mongodb_client.py
chain_factory/task_queue/wrapper/redis_client.py
chain_factory-0.0.5.dist-info/LICENSE
chain_factory-0.0.5.dist-info/METADATA
chain_factory-0.0.5.dist-info/WHEEL
chain_factory-0.0.5.dist-info/top_level.txt
chain_factory-0.0.5.dist-info/RECORD
